Metadata-Version: 1.0
Name: libmetric
Version: 0.1.0
Summary: Python library for querying metrics into Pandas DataFrames
Home-page: UNKNOWN
Author: UNKNOWN
Author-email: UNKNOWN
License: UNKNOWN
Platform: UNKNOWN
